README
setup.py
APNSWrapper/__init__.py
APNSWrapper/apnsexceptions.py
APNSWrapper/connection.py
APNSWrapper/feedback.py
APNSWrapper/notifications.py
APNSWrapper/utils.py
APNSWrapper.egg-info/PKG-INFO
APNSWrapper.egg-info/SOURCES.txt
APNSWrapper.egg-info/dependency_links.txt
APNSWrapper.egg-info/requires.txt
APNSWrapper.egg-info/top_level.txt